Workbook

Sheet Inputs
A1: Modelo Visual Studio Professional 2026 - Inputs corregidos
A3: Variable | B3: Valor | C3: Unidad | D3: Fuente / nota
A4: Total desarrolladores | B4: 40 | C4: usuarios | D4: Dato del caso
A5: Perpetuas VS Pro 2022 sin SA | B5: 26 | C5: usuarios | D5: Ya compradas; solo requieren SA para habilitar VS 2026
A6: Perpetuas VS Pro 2022 con SA vigente | B6: 10 | C6: usuarios | D6: Vencen a finales de este año; no se modela renovación
A7: Suscripciones Azure monthly actuales | B7: 4 | C7: usuarios | D7: Únicos usuarios que requerirían licencia nueva si salen de Azure monthly
A8: Precio SA anual por unidad SOLO para las 26 licencias perpetuas existentes | B8: 244.19 | C8: USD/año | D8: Cotización interna; no aplica a los 4 usuarios Azure
A9: Visual Studio Professional monthly | B9: 45 | C9: USD/usuario/mes | D9: Microsoft Visual Studio Pricing
A10: Visual Studio Professional standalone IDE | B10: 499 | C10: USD/usuario | D10: Microsoft Visual Studio Pricing; riesgo de ruta SA posterior
A11: Retailer LSA GitHub Year 1 | B11: 1019.94 | C11: USD/usuario | D11: Pagos Year 1/2/3 obligatorios
A12: Retailer LSA GitHub Year 2 | B12: 671.1 | C12: USD/usuario | D12: Pagos Year 1/2/3 obligatorios
A13: Retailer LSA GitHub Year 3 | B13: 322.26 | C13: USD/usuario | D13: Pagos Year 1/2/3 obligatorios
A14: Visual Studio Professional standard año 1 | B14: 99.99 | C14: USD/usuario/mes | D14: Microsoft Visual Studio Pricing
A15: Visual Studio Professional standard renovación | B15: 66.59 | C15: USD/usuario/mes | D15: Microsoft Visual Studio Pricing
... A19: Umbral descuento monthly | B19: 6 | C19: usuarios | D19: Desde el usuario 6 en adelante
A20: Renovar SA de las 10 existentes | B20: No | C20: Sí/No | D20: No se requiere si el objetivo es solo migrar a VS 2026
A21: Usar standalone como recomendación principal | B21: No | C21: Sí/No | D21: Riesgo: posible dificultad para comprar SA después
A22: Precio License + SA sin GitHub para 4 Azure | C22: USD/usuario | D22: Pendiente de cotización; alternativa preferible al SKU con GitHub si existe
A23: Aclaración crítica SA 244,19 | B23: Solo 26 licencias perpetuas existentes | C23: Alcance | D23: Las 26 ya tienen licencia perpetua; no se compra licencia nueva para ellas
A24: Nuevas licencias perpetuas potenciales | B24: 4 | C24: usuarios | D24: Solo aplicarían para los 4 usuarios que hoy están en Azure monthly
A25: Comprar nuevas licencias para las 26 perpetuas | B25: No | C25: Sí/No | D25: Incorrecto: las 26 licencias ya fueron compradas

Sheet Inventario actual
A1: Inventario actual y tratamiento correcto
A3: Grupo | B3: Cantidad | C3: Licencia actual | D3: Estado frente a VS 2026 | E3: Acción requerida | F3: Costo nuevo unitario USD | G3: Costo nuevo año 1 USD | H3: Observación
A4: Perpetuas VS Pro 2022 sin SA | B4: 26 | C4: Perpetua existente | D4: Elegibles para SA | E4: Comprar SA anual para habilitar VS 2026 | F4: 244.19 | G4: =B4*F4 -> 6348.94 | H4: No comprar licencia nueva; el costo correcto es SA.
A5: Perpetuas VS Pro 2022 con SA vigente | B5: 10 | C5: Perpetua + SA vigente | D5: Habilitadas para VS 2026 | E5: No renovar por ahora | F5: 0 | G5: =B5*F5 -> 0 | H5: Vencen a finales de año, pero no se requiere nueva actualización por ahora.
A6: Usuarios Azure monthly | B6: 4 | C6: Suscripción mensual | D6: Habilitados mientras se pague monthly | E6: Mantener o migrar a 4 licencias nuevas | F6: 45 | G6: =B6*F6*12 -> 2160 | H6: Solo estos 4 serían candidatos a licencia perpetua nueva.
A7: Nuevas licencias para las 26 | B7: 0 | C7: No aplica | D7: No aplica | E7: No comprar | F7: 499 | G7: =B7*F7 -> 0 | H7: Escenario incorrecto: esas 26 licencias ya existen.

Sheet Escenarios 3 años
A1: Escenarios de costo a 3 años - USD corregidos
A3: ID | B3: Escenario | C3: Año 1 USD | D3: Año 2 USD | E3: Año 3 USD | F3: Total 3 años USD | G3: Costo incremental vs recomendado | H3: Tipo gasto | I3: Derecho perpetuo | J3: Ruta SA futura | K3: Riesgo | L3: Recomendación | M3: Supuesto clave
A4: S1 | B4: Recomendado defendible: SA para 26 perpetuas existentes + mantener 4 Azure monthly | C4: =Inputs!$B$5*Inputs!$B$8 + Inputs!$B$7*Inputs!$B$9*12 -> 8508.94 | D4: =Inputs!$B$7*Inputs!$B$9*12 -> 2160 | E4: =Inputs!$B$7*Inputs!$B$9*12 -> 2160 | F4: =SUM(C4:E4) -> 12828.94 | G4: =F4-$F$4 -> 0 | H4: Mixto | I4: Sí para 36; Azure no | J4: Alta para 26/10; Azure por suscripción | K4: Bajo | L4: Recomendado | M4: SA USD 244,19 aplica solo a las 26 licencias perpetuas existentes. Los 4 Azure siguen como suscripción.
A5: S2 | B5: Menor costo con riesgo: SA para 26 perpetuas existentes + 4 nuevas standalone | C5: =Inputs!$B$5*Inputs!$B$8 + Inputs!$B$7*Inputs!$B$10 -> 8344.94 | D5: =0 -> 0 | E5: =0 -> 0 | F5: =SUM(C5:E5) -> 8344.94 | G5: =F5-$F$4 -> -4484 | H5: CAPEX/Mixto | I5: Sí | J5: Media/baja para 4 standalone | K5: Medio/alto | L5: No principal | M5: La compra de licencia perpetua nueva aplica solo a los 4 usuarios Azure. Riesgo: ruta futura de SA.
A6: S3 | B6: SA para 26 + 4 nuevas licencias retailer LSA GitHub | C6: =Inputs!$B$5*Inputs!$B$8 + Inputs!$B$7*Inputs!$B$11 -> 10428.7 | D6: =Inputs!$B$7*Inputs!$B$12 -> 2684.4 | E6: =Inputs!$B$7*Inputs!$B$13 -> 1289.04 | F6: =SUM(C6:E6) -> 14402.14 | G6: =F6-$F$4 -> 1573.2 | H6: Mixto | I6: Sí | J6: Alta mientras SA esté activa en los 4 nuevos | K6: Medio/alto | L6: Alternativa condicionada | M6: Corrige el error anterior: el retailer no se compra para 26; se compraría solo para 4 nuevos usuarios, pero incluye GitHub no usado.
A7: S4 | B7: Conservador: SA anual para 26 por 3 años + mantener 4 Azure monthly | C7: =Inputs!$B$5*Inputs!$B$8 + Inputs!$B$7*Inputs!$B$9*12 -> 8508.94 | D7: =Inputs!$B$5*Inputs!$B$8 + Inputs!$B$7*Inputs!$B$9*12 -> 8508.94 | E7: =Inputs!$B$5*Inputs!$B$8 + Inputs!$B$7*Inputs!$B$9*12 -> 8508.94 | F7: =SUM(C7:E7) -> 25526.82 | G7: =F7-$F$4 -> 12697.88 | H7: Mixto | I7: Sí para 36; Azure no | J7: Alta | K7: Bajo | L7: Alternativa segura | M7: Solo tiene sentido si quieren mantener derecho a nuevas versiones durante todo el horizonte.
A8: S5 | B8: Migrar los 40 usuarios a Azure monthly | C8: =((Inputs!$B$19-1)*Inputs!$B$9 + (Inputs!$B$4-Inputs!$B$19+1)*Inputs!$B$9*(1-Inputs!$B$18))*12 -> 20655 | D8: =C8 -> 20655 | E8: =C8 -> 20655 | F8: =SUM(C8:E8) -> 61965 | G8: =F8-$F$4 -> 49136.06 | H8: OPEX | I8: No | J8: Por suscripción | K8: Alto OPEX | L8: No recomendado | M8: Solo conviene si se prioriza flexibilidad total sobre costo.
A9: S6 | B9: Visual Studio Professional standard anual para 40 | C9: =Inputs!$B$4*Inputs!$B$14*12 -> 47995.2 | D9: =Inputs!$B$4*Inputs!$B$15*12 -> 31963.2 | E9: =Inputs!$B$4*Inputs!$B$15*12 -> 31963.2 | F9: =SUM(C9:E9) -> 111921.6 | G9: =F9-$F$4 -> 99092.66 | H9: OPEX | I9: No | J9: Por suscripción | K9: Costo muy alto | L9: No recomendado | M9: Incluye beneficios de suscripción, pero no responde al menor costo.

Sheet Resumen ejecutivo
A1: Resumen ejecutivo - decisión a 3 años
A3: Orden | B3: Escenario | C3: Año 1 USD | D3: Año 2 USD | E3: Año 3 USD | F3: Total 3 años USD | G3: Brecha vs recomendado | H3: Recomendación | I3: Riesgo | J3: Lectura ejecutiva | K3: Acción
A4: 1 | B4: S2 - Menor costo con riesgo: SA para 26 + 4 standalone | C4: ='Escenarios 3 años'!C5 -> 8344.94 | D4: ='Escenarios 3 años'!D5 -> 0 | E4: ='Escenarios 3 años'!E5 -> 0 | F4: ='Escenarios 3 años'!F5 -> 8344.94 | G4: ='Escenarios 3 años'!G5 -> -4484 | H4: No principal | I4: Medio/alto | J4: Más barato nominalmente, pero puede dificultar SA futura para los 4 usuarios. | K4: Usar solo si Microsoft/reseller confirma ruta futura de SA para standalone.
A5: 2 | B5: S1 - Recomendado: SA para 26 + mantener 4 Azure | C5: ='Escenarios 3 años'!C4 -> 8508.94 | D5: ='Escenarios 3 años'!D4 -> 2160 | E5: ='Escenarios 3 años'!E4 -> 2160 | F5: ='Escenarios 3 años'!F4 -> 12828.94 | G5: ='Escenarios 3 años'!G4 -> 0 | H5: Recomendado | I5: Bajo | J5: Aprovecha las 26 licencias existentes y evita comprar licencias nuevas para ellas. | K5: Comprar SA para 26; mantener Azure mientras se cotiza License + SA sin GitHub para 4.
A6: 3 | B6: S3 - Retailer correcto: SA 26 + 4 nuevas retailer LSA GitHub | C6: ='Escenarios 3 años'!C6 -> 10428.7 | D6: ='Escenarios 3 años'!D6 -> 2684.4 | E6: ='Escenarios 3 años'!E6 -> 1289.04 | F6: ='Escenarios 3 años'!F6 -> 14402.14 | G6: ='Escenarios 3 años'!G6 -> 1573.2 | H6: Alternativa condicionada | I6: Medio/alto | J6: Corrige el alcance: retailer solo para 4 nuevos usuarios, no para 26. | K6: Evaluar solo si no existe License + SA sin GitHub para 4.
A7: 4 | B7: S4 - Conservador: SA anual 26 por 3 años + mantener 4 Azure | C7: ='Escenarios 3 años'!C7 -> 8508.94 | D7: ='Escenarios 3 años'!D7 -> 8508.94 | E7: ='Escenarios 3 años'!E7 -> 8508.94 | F7: ='Escenarios 3 años'!F7 -> 25526.82 | G7: ='Escenarios 3 años'!G7 -> 12697.88 | H7: Alternativa segura | I7: Bajo | J7: Mantiene New Version Rights para las 26 durante todo el horizonte. | K7: Usar si la estrategia exige actualización futura continua.
A8: 5 | B8: S5 - Todos Azure monthly | C8: ='Escenarios 3 años'!C8 -> 20655 | D8: ='Escenarios 3 años'!D8 -> 20655 | E8: ='Escenarios 3 años'!E8 -> 20655 | F8: ='Escenarios 3 años'!F8 -> 61965 | G8: ='Escenarios 3 años'!G8 -> 49136.06 | H8: No recomendado | I8: Alto OPEX | J8: Flexible pero caro a 3 años. | K8: Descartar por costo.
A9: 6 | B9: S6 - Standard anual para 40 | C9: ='Escenarios 3 años'!C9 -> 47995.2 | D9: ='Escenarios 3 años'!D9 -> 31963.2 | E9: ='Escenarios 3 años'!E9 -> 31963.2 | F9: ='Escenarios 3 años'!F9 -> 111921.6 | G9: ='Escenarios 3 años'!G9 -> 99092.66 | H9: No recomendado | I9: Muy alto costo | J9: Máximo costo entre escenarios modelados. | K9: Descartar por costo.

Sheet Validaciones
A1: Validaciones y estado
A3: Validación | B3: Estado | C3: Por qué importa | D3: Impacto sí | E3: Impacto no | F3: Responsable sugerido | G3: Nota
A4: Elegibilidad de las 26 perpetuas para adquirir SA | B4: Confirmado: Sí | C4: Permite usar SA de USD 244,19 sin recomprar licencias | D4: S1/S4 válidos | E4: Habría que recomprar o usar suscripción | F4: Reseller/Microsoft | G4: Confirmado por usuario
A5: SA otorga New Version Rights | B5: Confirmado: Sí | C5: Habilita migración a VS 2026 con SA activa | D5: Se puede actualizar licencias cubiertas | E5: SA no serviría para objetivo | F5: Microsoft/Reseller | G5: Fuente Microsoft
A6: Naturaleza del pago SA | B6: Confirmado: Anual | C6: Evita tratar SA como pago único multianual | D6: Se modela como anual | E6: Cambiaría total 3 años | F6: Compras/Reseller | G6: En S1 solo se compra año 1 por objetivo VS 2026
A7: Year 1/2/3 retailer obligatorios | B7: Confirmado: Sí | C7: Hace más costosa la opción retailer | D7: S3 debe incluir 3 pagos | E7: No se podría comparar igual | F7: Reseller | G7: Confirmado por usuario
A8: Retailer es License + SA | B8: Confirmado: Sí | C8: Sirve para licencias nuevas, no para las 26 existentes | D8: Aplica a los 4 Azure si se reemplazan | E8: No usar como alternativa de licenciamiento | F8: Reseller | G8: Después se paga SA al vencer
A9: Cotización incluye GitHub Enterprise | B9: No se usa en la compañía | C9: Reduce valor práctico del SKU | D9: No aporta al caso | E9: Podría descartarse | F9: Compras/TI | G9: Confirmado por usuario: no usan GitHub
A10: Derecho perpetuo al finalizar retailer | B10: Confirmado: Sí | C10: Importa para CAPEX y continuidad | D10: Queda licencia perpetua | E10: No sería comparable | F10: Reseller | G10: Se requiere SA para futuras actualizaciones
A11: Migrar los 4 Azure a otro modelo | B11: Confirmado: Posible | C11: Permite evaluar licencias nuevas solo para 4 | D11: Opciones S2/S3 válidas | E11: Se mantiene Azure monthly | F11: TI/Compras | G11: Suscripción mensual flexible
A12: License + SA sin GitHub para 4 Azure | B12: Confirmado: No es posible | C12: Sería mejor que comprar SKU con GitHub que no usan | D12: Puede reemplazar S3 por opción más eficiente | E12: S3 queda como referencia costosa | F12: Reseller | G12: Cotizar solo 4 usuarios

Sheet Fuentes y supuestos
A1: Fuentes y supuestos
A3: Fuente | B3: Dato usado | C3: URL | D3: Fecha consulta | E3: Tipo | F3: Observación
A4: Microsoft Visual Studio Pricing | B4: Professional monthly USD 45; standard USD 99,99; renewal USD 66,59; standalone USD 499 | C4: https://visualstudio.microsoft.com/vs/pricing/?tab=paid-subscriptions | D4: 2026-05-20 | E4: Oficial | F4: Precios de referencia públicos
A5: Microsoft Software Assurance Benefits | B5: New Version Rights para licencias cubiertas con SA activa | C5: https://www.microsoft.com/en-us/licensing/licensing-programs/software-assurance-by-benefits | D5: 2026-05-20 | E5: Oficial | F5: Sustenta migración con SA activa
A6: Cotización interna retailer | B6: VS Pro with GitHub ALng LSA Year 1/2/3 | C6: Cotización interna / reseller | D6: 2026-05-20 | E6: Interna | F6: Pagos obligatorios según validación del usuario
A7: Validación usuario | B7: 26 licencias elegibles para SA; SA anual; 4 Azure migrables | C7: Conversación de trabajo | D7: 2026-05-20 | E7: Interna | F7: Modelo en USD únicamente
A8: Supuesto principal | B8: Objetivo: solo habilitar Visual Studio 2026 | C8: Conversación de trabajo | D8: 2026-05-20 | E8: Supuesto | F8: No renovar SA de 10 existentes ni continuidad multiversión salvo escenario S4

Sheet Recomendación gerencia
A1: Recomendación para gerencia
A3: Conclusión principal | B3: El escenario retailer anterior estaba mal planteado. No corresponde comprar retailer para 26 licencias porque esas 26 ya existen; solo requieren SA anual de USD 244,19 por unidad. Si se compran nuevas licencias perpetuas, serían únicamente para los 4 usuarios que hoy están en Azure monthly.
A4: Opción recomendada | B4: Comprar SA anual para las 26 licencias perpetuas existentes y mantener temporalmente los 4 usuarios Azure monthly.
A5: Costo recomendado a 3 años | B5: ='Escenarios 3 años'!F4 -> 12828.94
A6: Costo correcto del SA | B6: 26 × USD 244,19 = USD 6.348,94. Aplica solo a las 26 licencias perpetuas existentes.
A7: Retailer corregido | B7: La alternativa retailer correcta es 26 SA + 4 nuevas licencias retailer LSA GitHub, no retailer para 26 + mantener 4 Azure.
A8: Costo retailer corregido | B8: ='Escenarios 3 años'!F6 -> 14402.14
A9: Por qué no es principal | B9: El SKU retailer tiene pagos Year 1/2/3 obligatorios e incluye GitHub, que la compañía no usa.
A10: Riesgo standalone | B10: Standalone para los 4 usuarios Azure es más barato, pero no queda como recomendación principal por posible dificultad de adquirir SA después.
A11: Acción inmediata | B11: Comprar SA para 26 y cotizar una opción License + SA sin GitHub únicamente para los 4 usuarios Azure.
A12: Mensaje sugerido | B12: La decisión debe separar dos universos: 26 licencias ya compradas que solo requieren SA, y 4 usuarios Azure que sí podrían requerir licencia nueva si se decide salir de suscripción.
A13: Estado | B13: Documento corregido con horizonte 3 años en USD.

Sheet Gráficos
A1: Gráficos - costos a 3 años USD
A3: Escenario | B3: Año 1 USD | C3: Año 2 USD | D3: Año 3 USD | E3: Total 3 años USD
A4: S1 Recomendado | B4: ='Escenarios 3 años'!C4 -> 8508.94 | C4: ='Escenarios 3 años'!D4 -> 2160 | D4: ='Escenarios 3 años'!E4 -> 2160 | E4: ='Escenarios 3 años'!F4 -> 12828.94
A5: S2 Barato con riesgo | B5: ='Escenarios 3 años'!C5 -> 8344.94 | C5: ='Escenarios 3 años'!D5 -> 0 | D5: ='Escenarios 3 años'!E5 -> 0 | E5: ='Escenarios 3 años'!F5 -> 8344.94
A6: S3 Retailer correcto 4 | B6: ='Escenarios 3 años'!C6 -> 10428.7 | C6: ='Escenarios 3 años'!D6 -> 2684.4 | D6: ='Escenarios 3 años'!E6 -> 1289.04 | E6: ='Escenarios 3 años'!F6 -> 14402.14
A7: S4 Conservador | B7: ='Escenarios 3 años'!C7 -> 8508.94 | C7: ='Escenarios 3 años'!D7 -> 8508.94 | D7: ='Escenarios 3 años'!E7 -> 8508.94 | E7: ='Escenarios 3 años'!F7 -> 25526.82
A8: S5 Azure monthly | B8: ='Escenarios 3 años'!C8 -> 20655 | C8: ='Escenarios 3 años'!D8 -> 20655 | D8: ='Escenarios 3 años'!E8 -> 20655 | E8: ='Escenarios 3 años'!F8 -> 61965
A9: S6 Standard anual | B9: ='Escenarios 3 años'!C9 -> 47995.2 | C9: ='Escenarios 3 años'!D9 -> 31963.2 | D9: ='Escenarios 3 años'!E9 -> 31963.2 | E9: ='Escenarios 3 años'!F9 -> 111921.6

Sheet Aclaración alcance
A1: Aclaración de alcance de licenciamiento
A3: Tema | B3: Cantidad | C3: Costo unitario USD | D3: Costo año 1 USD | E3: Qué significa | F3: Decisión
A4: SA para licencias perpetuas existentes | B4: 26 | C4: 244.19 | D4: =B4*C4 -> 6348.94 | E4: Aplica solo a las 26 licencias perpetuas ya compradas. No es compra de licencia nueva. | F4: Comprar SA para habilitar VS 2026
A5: Licencias perpetuas con SA vigente | B5: 10 | C5: 0 | D5: =B5*C5 -> 0 | E5: Ya permiten migrar a VS 2026. No se renuevan en el caso base. | F5: No comprar ni renovar por ahora
A6: Usuarios Azure monthly actuales | B6: 4 | C6: 45 | D6: =B6*C6*12 -> 2160 | E6: Siguen habilitados mientras se pague suscripción. | F6: Mantener temporalmente o migrar a licencia nueva
A7: Nuevas licencias potenciales | B7: 4 | C7: 499 | D7: =B7*C7 -> 1996 | E7: Solo serían para los 4 usuarios Azure si se decide salir de suscripción. | F7: Cotizar alternativa con ruta de SA futura
A8: Nuevas licencias para las 26 existentes | B8: 0 | C8: 499 | D8: =B8*C8 -> 0 | E8: No corresponde: esas 26 ya tienen Visual Studio Professional 2022 perpetuo. | F8: No comprar
